reggie/__init__.py
reggie/_version.py
reggie-0.1.dist-info/DESCRIPTION.rst
reggie-0.1.dist-info/METADATA
reggie-0.1.dist-info/RECORD
reggie-0.1.dist-info/WHEEL
reggie-0.1.dist-info/metadata.json
reggie-0.1.dist-info/top_level.txt
reggie-0.1.dist-info/zip-safe
