Metadata-Version: 2.0
Name: reggie
Version: 0.1
Summary: Reggie the Registration and Management System
Home-page: http://reggie.readthedocs.org
Author: Rob Ruana
Author-email: rob@robruana.com
License: BSD
Download-URL: http://pypi.python.org/pypi/reggie
Platform: any
Classifier: Development Status :: 1 - Planning
Classifier: Environment :: Console
Classifier: Environment :: Web Environment
Classifier: Intended Audience :: Developers
Classifier: License :: OSI Approved :: BSD License
Classifier: Operating System :: OS Independent
Classifier: Programming Language :: Python
Classifier: Programming Language :: Python :: 2
Classifier: Programming Language :: Python :: 3
Classifier: Topic :: Utilities
Classifier: Topic :: Education
Classifier: Topic :: Internet :: WWW/HTTP
Classifier: Topic :: Office/Business
Classifier: Topic :: Office/Business :: Groupware
Classifier: Topic :: Office/Business :: Scheduling
Requires-Dist: pockets (>=0.5.1)
Requires-Dist: residue (>=0.1)
Requires-Dist: six (>=1.5.2)
